{
  "games": [
    {
      "name": "Just Another Regular Arcade",
      "git": "https://github.com/turnercode/cn-games_regular-show_jara",
      "branch": "develop"
    }
  ],
  "privacyAndTerms": {
    "expectedDate": "October 8, 2018"
  },
  "projectConfig": "ProjectSettings.asset",
  "targets": {
    "Android": {
      "scriptingBackend": 1,
      "targetArchitectures": ["ARM64"],
      "targetApi": 28
    },
    "iOS": {
      "scriptingBackend": 1
    }
  },
  "DFP": {
    "expectedMD5Sum": "bead580e9ba12fee1abb8064d6cf7340"
  }
}